actors/__init__.py
actors/actors/__init__.py
actors/actors/base.py
actors/actors/openai.py
actors/actors/vllm.py
actors/environments/__init__.py
actors/environments/actors_schedule_dsl.py
actors/environments/collaborative_env.py
actors/environments/env_base.py
actors/environments/masking.py
actors/environments/parallel_environment.py
actors/environments/single_turn_env.py
actors/environments/types.py
actors/inference/__init__.py
actors/inference/pool.py
actors/inference/rlhf_utils.py
actors/inference/worker.py
actors/losses/__init__.py
actors/losses/base_loss.py
actors/losses/grpo_loss.py
actors/losses/gspo_loss.py
actors/losses/liger_grpo_loss.py
actors/losses/liger_gspo_loss.py
actors/rewards/__init__.py
actors/rewards/base_completion_reward.py
actors/rewards/base_conversation_reward.py
actors/trainers/__init__.py
actors/trainers/base_config.py
actors/trainers/base_trainer.py
actors/trainers/grpo_config.py
actors/trainers/grpo_trainer.py
actors/utils/__init__.py
actors/utils/accelerate.py
actors/utils/data.py
actors/utils/deepspeed.py
actors/utils/get_logps.py
actors/utils/gspo_loss.py
actors/utils/ipc_utils.py
actors/utils/logger.py
actors/utils/monkey_patch_unsloth_gradient_checkpointing.py
actors/utils/softmax.py
actors/utils/tracker.py
actors/utils/train_utils.py
actors/utils/vllm.py
actors/utils/wandb.py
rl_actors-0.1.2.dist-info/licenses/LICENSE
rl_actors-0.1.2.dist-info/METADATA
rl_actors-0.1.2.dist-info/WHEEL
rl_actors-0.1.2.dist-info/top_level.txt
rl_actors-0.1.2.dist-info/RECORD
