Metadata-Version: 2.4
Name: rl-actors
Version: 0.1.2
Summary: Actors: A hackable library for doing Multi-Turn Multi-Agent RL with LLMs for the GPU poor and middle class.
Author-email: David Dinucu-Jianu <david.dinucujianu@gmail.com>
Project-URL: Homepage, https://github.com/RD211/actors
Project-URL: Bug Tracker, https://github.com/RD211/actors/issues
Project-URL: Repository, https://github.com/RD211/actors
Project-URL: Documentation, https://github.com/RD211/actors#readme
Keywords: reinforcement learning,llm,grpo,ai
Classifier: Development Status :: 3 - Alpha
Classifier: Intended Audience :: Developers
Classifier: Intended Audience :: Science/Research
Classifier: License :: OSI Approved :: MIT License
Classifier: Operating System :: OS Independent
Classifier: Programming Language :: Python :: 3
Classifier: Programming Language :: Python :: 3.10
Classifier: Programming Language :: Python :: 3.11
Classifier: Programming Language :: Python :: 3.12
Classifier: Topic :: Scientific/Engineering :: Artificial Intelligence
Classifier: Topic :: Software Development :: Libraries :: Python Modules
Requires-Python: >=3.8
License-File: LICENSE
Requires-Dist: vllm>=0.9.1
Requires-Dist: deepspeed>=0.17.1
Requires-Dist: liger-kernel>=0.5.10
Requires-Dist: ninja
Requires-Dist: accelerate
Requires-Dist: transformers<4.54.0
Requires-Dist: datasets
Requires-Dist: pynvml
Requires-Dist: psutil
Requires-Dist: bitsandbytes
Requires-Dist: torch
Requires-Dist: peft>=0.15.2
Requires-Dist: wandb
Requires-Dist: ray
Requires-Dist: math-verify>=0.8.0
Requires-Dist: colorama
Requires-Dist: nest_asyncio
Provides-Extra: dev
Requires-Dist: pytest>=7.0; extra == "dev"
Requires-Dist: pytest-cov; extra == "dev"
Requires-Dist: ruff; extra == "dev"
Requires-Dist: mypy; extra == "dev"
Requires-Dist: pre-commit; extra == "dev"
Requires-Dist: pytest-asyncio; extra == "dev"
Provides-Extra: docs
Requires-Dist: mkdocs; extra == "docs"
Requires-Dist: mkdocs-material; extra == "docs"
Requires-Dist: mkdocstrings[python]; extra == "docs"
Dynamic: license-file
